pct_python_default_test/__init__.py
pct_python_default_test/__init__conf__.py
pct_python_default_test/pct_python_default_test.py
pct_python_default_test/pct_python_default_test_cli.py
pct_python_default_test/py.typed
pct_python_default_test-1.0.9.dist-info/LICENSE
pct_python_default_test-1.0.9.dist-info/METADATA
pct_python_default_test-1.0.9.dist-info/WHEEL
pct_python_default_test-1.0.9.dist-info/entry_points.txt
pct_python_default_test-1.0.9.dist-info/top_level.txt
pct_python_default_test-1.0.9.dist-info/RECORD
