Metadata-Version: 2.1
Name: pct_python_default_test
Version: 1.0.9
Summary: a pizzacutter default test project, crated with PizzaCutter and the PizzaCutter default python template
Author-email: Robert Nowotny <bitranox@gmail.com>
License: MIT
Project-URL: Homepage, https://github.com/bitranox/pct_python_default_test
Project-URL: Documentation, https://github.com/bitranox/pct_python_default_test/blob/master/README.rst
Project-URL: Repository, https://github.com/bitranox/pct_python_default_test.git
Project-URL: Changelog, https://github.com/bitranox/pct_python_default_test/blob/master/CHANGES.rst
Classifier: Development Status :: 5 - Production/Stable
Classifier: Intended Audience :: Developers
Classifier: License :: OSI Approved :: MIT License
Classifier: Natural Language :: English
Classifier: Operating System :: OS Independent
Classifier: Programming Language :: Python
Classifier: Topic :: Software Development :: Libraries :: Python Modules
Requires-Python: >=3.8.0
License-File: LICENSE
Requires-Dist: cli-exit-tools
Requires-Dist: click
Provides-Extra: test
Requires-Dist: black ; extra == 'test'
Requires-Dist: codecov ; extra == 'test'
Requires-Dist: coloredlogs ; extra == 'test'
Requires-Dist: coverage ; extra == 'test'
Requires-Dist: flake8 ; extra == 'test'
Requires-Dist: mypy ; extra == 'test'
Requires-Dist: pytest ; extra == 'test'
Requires-Dist: pytest-cov ; extra == 'test'
Requires-Dist: pytest-runner ; extra == 'test'
Requires-Dist: readme-renderer ; extra == 'test'
